gplay_scraper/__init__.py
gplay_scraper/app.py
gplay_scraper/config.py
gplay_scraper/exceptions.py
gplay_scraper/core/__init__.py
gplay_scraper/core/gplay_methods.py
gplay_scraper/core/gplay_parser.py
gplay_scraper/core/gplay_scraper.py
gplay_scraper/models/__init__.py
gplay_scraper/models/element_specs.py
gplay_scraper/utils/__init__.py
gplay_scraper/utils/constants.py
gplay_scraper/utils/error_handling.py
gplay_scraper/utils/helpers.py
gplay_scraper/utils/http_client.py
gplay_scraper-1.0.6.dist-info/licenses/LICENSE
gplay_scraper-1.0.6.dist-info/METADATA
gplay_scraper-1.0.6.dist-info/WHEEL
gplay_scraper-1.0.6.dist-info/top_level.txt
gplay_scraper-1.0.6.dist-info/RECORD
