Metadata-Version: 2.4
Name: gplay-scraper
Version: 1.0.6
Summary: 🚀 Advanced Google Play Store Scraper - Extract 65+ app fields, reviews, ratings, ASO data, developer info, top charts, search results with 7 HTTP clients & unlimited pagination support
Home-page: https://github.com/mohammedcha/gplay-scraper
Download-URL: https://github.com/mohammedcha/gplay-scraper/archive/v1.0.6.tar.gz
Author: Mohammed Cha
Author-email: contact@mohammedcha.com
Maintainer: Mohammed Cha
Maintainer-email: contact@mohammedcha.com
Project-URL: Homepage, https://github.com/mohammedcha/gplay-scraper
Project-URL: Documentation, https://mohammedcha.github.io/gplay-scraper/
Project-URL: Source Code, https://github.com/mohammedcha/gplay-scraper
Project-URL: Bug Reports, https://github.com/mohammedcha/gplay-scraper/issues
Project-URL: Feature Requests, https://github.com/mohammedcha/gplay-scraper/issues
Project-URL: Changelog, https://github.com/mohammedcha/gplay-scraper/blob/main/CHANGELOG.md
Project-URL: Examples, https://github.com/mohammedcha/gplay-scraper/tree/main/examples
Project-URL: PyPI, https://pypi.org/project/gplay-scraper/
Keywords: google-play-scraper,playstore-scraper,android-scraper,gplay-scraper,google-play-store,play-store-api,app-data-extraction,app-analytics,mobile-analytics,aso-tools,app-store-optimization,mobile-seo,app-marketing,keyword-research,competitor-analysis,market-research,app-reviews,user-reviews,review-scraper,rating-analysis,sentiment-analysis,developer-tools,api-scraping,web-scraping,data-mining,python-scraper,automation-tools,business-intelligence,market-intelligence,competitive-intelligence
Platform: any
Classifier: Development Status :: 5 - Production/Stable
Classifier: Intended Audience :: Developers
Classifier: Intended Audience :: Information Technology
Classifier: Intended Audience :: Science/Research
Classifier: Intended Audience :: Financial and Insurance Industry
Classifier: License :: OSI Approved :: MIT License
Classifier: Operating System :: OS Independent
Classifier: Operating System :: Microsoft :: Windows
Classifier: Operating System :: POSIX :: Linux
Classifier: Operating System :: MacOS
Classifier: Programming Language :: Python :: 3
Classifier: Programming Language :: Python :: 3.8
Classifier: Programming Language :: Python :: 3.9
Classifier: Programming Language :: Python :: 3.10
Classifier: Programming Language :: Python :: 3.11
Classifier: Programming Language :: Python :: 3.12
Classifier: Programming Language :: Python :: 3 :: Only
Classifier: Topic :: Internet :: WWW/HTTP :: Dynamic Content
Classifier: Topic :: Internet :: WWW/HTTP :: Indexing/Search
Classifier: Topic :: Software Development :: Libraries :: Python Modules
Classifier: Topic :: Software Development :: Libraries :: Application Frameworks
Classifier: Topic :: Utilities
Classifier: Topic :: Scientific/Engineering :: Information Analysis
Classifier: Topic :: Office/Business :: Financial :: Investment
Classifier: Topic :: Internet :: WWW/HTTP :: Browsers
Classifier: Topic :: Text Processing :: Markup :: HTML
Classifier: Topic :: Database
Classifier: Natural Language :: English
Classifier: Environment :: Console
Classifier: Environment :: Web Environment
Classifier: Framework :: AsyncIO
Classifier: Typing :: Typed
Requires-Python: >=3.8
License-File: LICENSE
Requires-Dist: requests>=2.25.0
Requires-Dist: beautifulsoup4>=4.9.0
Requires-Dist: curl-cffi>=0.5.0
Requires-Dist: tls-client>=1.0.0
Requires-Dist: urllib3>=1.26.0
Requires-Dist: cloudscraper>=1.2.0
Requires-Dist: aiohttp>=3.8.0
Requires-Dist: httpx>=0.24.0
Requires-Dist: pytest>=6.0.0
Requires-Dist: sphinx>=4.0.0
Requires-Dist: sphinx-rtd-theme>=1.0.0
Provides-Extra: dev
Requires-Dist: pytest>=7.0.0; extra == "dev"
Requires-Dist: pytest-cov>=4.0.0; extra == "dev"
Requires-Dist: black>=22.0.0; extra == "dev"
Requires-Dist: flake8>=5.0.0; extra == "dev"
Provides-Extra: http-clients
Requires-Dist: curl-cffi>=0.5.0; extra == "http-clients"
Requires-Dist: tls-client>=0.2.0; extra == "http-clients"
Requires-Dist: httpx>=0.24.0; extra == "http-clients"
Requires-Dist: urllib3>=1.26.0; extra == "http-clients"
Requires-Dist: cloudscraper>=1.2.0; extra == "http-clients"
Requires-Dist: aiohttp>=3.8.0; extra == "http-clients"
Provides-Extra: all
Requires-Dist: pytest>=7.0.0; extra == "all"
Requires-Dist: pytest-cov>=4.0.0; extra == "all"
Requires-Dist: black>=22.0.0; extra == "all"
Requires-Dist: flake8>=5.0.0; extra == "all"
Requires-Dist: curl-cffi>=0.5.0; extra == "all"
Requires-Dist: tls-client>=0.2.0; extra == "all"
Requires-Dist: httpx>=0.24.0; extra == "all"
Requires-Dist: urllib3>=1.26.0; extra == "all"
Requires-Dist: cloudscraper>=1.2.0; extra == "all"
Requires-Dist: aiohttp>=3.8.0; extra == "all"
Dynamic: author
Dynamic: author-email
Dynamic: classifier
Dynamic: description
Dynamic: description-content-type
Dynamic: download-url
Dynamic: home-page
Dynamic: keywords
Dynamic: license-file
Dynamic: maintainer
Dynamic: maintainer-email
Dynamic: platform
Dynamic: project-url
Dynamic: provides-extra
Dynamic: requires-dist
Dynamic: requires-python
Dynamic: summary
